custom_time/__init__.py
custom_time/custom_time.py
custom_time/time_range.py
custom_time-1.0.dist-info/LICENCE
custom_time-1.0.dist-info/METADATA
custom_time-1.0.dist-info/WHEEL
custom_time-1.0.dist-info/top_level.txt
custom_time-1.0.dist-info/RECORD
