Metadata-Version: 2.1
Name: custom_time
Version: 1.0
Summary: UNKNOWN
Home-page: UNKNOWN
Author: YangBiao
Author-email: 19921297590@126.com
License: MIT License
Platform: all
License-File: LICENCE
